yeller.py
yeller-0.0.8.data/scripts/hello.py
yeller-0.0.8.data/scripts/install_dev.py
yeller-0.0.8.data/scripts/redhat.sh
yeller-0.0.8.data/scripts/rocky.sh
yeller-0.0.8.data/scripts/ubuntu.sh
yeller-0.0.8.data/scripts/version.py
yeller-0.0.8.data/scripts/windows.ps1
yeller-0.0.8.dist-info/METADATA
yeller-0.0.8.dist-info/WHEEL
yeller-0.0.8.dist-info/entry_points.txt
yeller-0.0.8.dist-info/top_level.txt
yeller-0.0.8.dist-info/RECORD
