Metadata-Version: 2.1
Name: yeller
Version: 0.0.8
Home-page: https://github.com/oimoulder/yeller
Author: Josh Moulder
Author-email: josh.moulder12@gmail.com
Keywords: cli automation devops sre plugin
Classifier: Development Status :: 1 - Planning
Classifier: Environment :: Console
Classifier: Intended Audience :: Developers
Classifier: Intended Audience :: System Administrators
Classifier: License :: OSI Approved :: MIT License
Classifier: Operating System :: OS Independent
Classifier: Programming Language :: Python :: 3.10
Classifier: Topic :: Terminals
Classifier: Topic :: Utilities
Requires-Dist: Click
